{
    "rx.BackpressureTests": 758,
    "rx.CombineLatestTests": 174,
    "rx.ConcatTests": 172,
    "rx.CovarianceTest": 162,
    "rx.ErrorHandlingTests": 379,
    "rx.EventStream": 189,
    "rx.GroupByTests": 190,
    "rx.IntervalDemo": 185,
    "rx.MergeTests": 175,
    "rx.Notification": 42,
    "rx.Observable": 43,
    "rx.ObservableDoOnTest": 308,
    "rx.ObservableTests": 160,
    "rx.ObservableWindowTests": 166,
    "rx.Observer": 451,
    "rx.PerfBaseline": 723,
    "rx.Producer": 750,
    "rx.ReduceTests": 176,
    "rx.ScanTests": 191,
    "rx.Scheduler": 93,
    "rx.StartWithTests": 173,
    "rx.Subscriber": 44,
    "rx.SubscriberTest": 759,
    "rx.Subscription": 38,
    "rx.ThrottleLastTests": 294,
    "rx.ThrottleWithTimeoutTests": 179,
    "rx.ZipTests": 177,
    "rx.exceptions.CompositeException": 37,
    "rx.exceptions.CompositeExceptionTest": 460,
    "rx.exceptions.Exceptions": 81,
    "rx.exceptions.ExceptionsTest": 477,
    "rx.exceptions.MissingBackpressureException": 751,
    "rx.exceptions.OnErrorFailedException": 591,
    "rx.exceptions.OnErrorNotImplementedException": 142,
    "rx.exceptions.OnErrorThrowable": 534,
    "rx.exceptions.OnNextValueTest": 749,
    "rx.exceptions.TestException": 670,
    "rx.functions.Action": 155,
    "rx.functions.Action0": 61,
    "rx.functions.Action1": 62,
    "rx.functions.Action2": 63,
    "rx.functions.Action3": 64,
    "rx.functions.Action4": 338,
    "rx.functions.Action5": 339,
    "rx.functions.Action6": 340,
    "rx.functions.Action7": 341,
    "rx.functions.Action8": 342,
    "rx.functions.Action9": 343,
    "rx.functions.ActionN": 344,
    "rx.functions.Actions": 328,
    "rx.functions.Func0": 5,
    "rx.functions.Func1": 6,
    "rx.functions.Func2": 7,
    "rx.functions.Func3": 8,
    "rx.functions.Func4": 9,
    "rx.functions.Func5": 50,
    "rx.functions.Func6": 51,
    "rx.functions.Func7": 52,
    "rx.functions.Func8": 53,
    "rx.functions.Func9": 54,
    "rx.functions.FuncN": 10,
    "rx.functions.Function": 65,
    "rx.functions.Functions": 11,
    "rx.internal.IndexedRingBufferPerf": 755,
    "rx.internal.RxRingBufferPerf": 756,
    "rx.internal.operators.BlockingOperatorLatest": 381,
    "rx.internal.operators.BlockingOperatorLatestTest": 382,
    "rx.internal.operators.BlockingOperatorMostRecent": 84,
    "rx.internal.operators.BlockingOperatorMostRecentTest": 247,
    "rx.internal.operators.BlockingOperatorNext": 82,
    "rx.internal.operators.BlockingOperatorNextTest": 249,
    "rx.internal.operators.BlockingOperatorToFuture": 129,
    "rx.internal.operators.BlockingOperatorToFutureTest": 292,
    "rx.internal.operators.BlockingOperatorToIterator": 89,
    "rx.internal.operators.BlockingOperatorToIteratorTest": 293,
    "rx.internal.operators.BufferUntilSubscriber": 498,
    "rx.internal.operators.BufferUntilSubscriberTest": 786,
    "rx.internal.operators.NotificationLite": 584,
    "rx.internal.operators.NotificationLiteTest": 729,
    "rx.internal.operators.OnBackpressureBlockTest": 803,
    "rx.internal.operators.OnSubscribeAmb": 219,
    "rx.internal.operators.OnSubscribeAmbTest": 295,
    "rx.internal.operators.OnSubscribeCache": 137,
    "rx.internal.operators.OnSubscribeCacheTest": 585,
    "rx.internal.operators.OnSubscribeCombineLatest": 617,
    "rx.internal.operators.OnSubscribeCombineLatestTest": 618,
    "rx.internal.operators.OnSubscribeDefer": 85,
    "rx.internal.operators.OnSubscribeDeferTest": 233,
    "rx.internal.operators.OnSubscribeDelaySubscription": 668,
    "rx.internal.operators.OnSubscribeDelaySubscriptionWithSelector": 787,
    "rx.internal.operators.OnSubscribeFromIterable": 428,
    "rx.internal.operators.OnSubscribeFromIterableTest": 271,
    "rx.internal.operators.OnSubscribeGroupJoin": 356,
    "rx.internal.operators.OnSubscribeGroupJoinTest": 358,
    "rx.internal.operators.OnSubscribeJoin": 636,
    "rx.internal.operators.OnSubscribeJoinTest": 331,
    "rx.internal.operators.OnSubscribeMulticastSelector": 640,
    "rx.internal.operators.OnSubscribeMulticastTest": 248,
    "rx.internal.operators.OnSubscribeRange": 481,
    "rx.internal.operators.OnSubscribeRangeTest": 483,
    "rx.internal.operators.OnSubscribeRedo": 769,
    "rx.internal.operators.OnSubscribeRefCount": 648,
    "rx.internal.operators.OnSubscribeRefCountTest": 792,
    "rx.internal.operators.OnSubscribeTimerOnce": 632,
    "rx.internal.operators.OnSubscribeTimerPeriodically": 633,
    "rx.internal.operators.OnSubscribeTimerTest": 242,
    "rx.internal.operators.OnSubscribeToObservableFuture": 69,
    "rx.internal.operators.OnSubscribeToObservableFutureTest": 270,
    "rx.internal.operators.OnSubscribeUsing": 643,
    "rx.internal.operators.OnSubscribeUsingTest": 306,
    "rx.internal.operators.OperatorAll": 561,
    "rx.internal.operators.OperatorAllTest": 602,
    "rx.internal.operators.OperatorAny": 610,
    "rx.internal.operators.OperatorAnyTest": 224,
    "rx.internal.operators.OperatorAsObservable": 392,
    "rx.internal.operators.OperatorAsObservableTest": 611,
    "rx.internal.operators.OperatorBufferTest": 226,
    "rx.internal.operators.OperatorBufferWithSingleObservable": 612,
    "rx.internal.operators.OperatorBufferWithSize": 613,
    "rx.internal.operators.OperatorBufferWithStartEndObservable": 614,
    "rx.internal.operators.OperatorBufferWithTime": 615,
    "rx.internal.operators.OperatorCast": 432,
    "rx.internal.operators.OperatorCastTest": 228,
    "rx.internal.operators.OperatorConcat": 616,
    "rx.internal.operators.OperatorConcatTest": 230,
    "rx.internal.operators.OperatorDebounceTest": 231,
    "rx.internal.operators.OperatorDebounceWithSelector": 627,
    "rx.internal.operators.OperatorDebounceWithTime": 628,
    "rx.internal.operators.OperatorDefaultIfEmpty": 619,
    "rx.internal.operators.OperatorDefaultIfEmptyTest": 620,
    "rx.internal.operators.OperatorDelay": 788,
    "rx.internal.operators.OperatorDelayTest": 362,
    "rx.internal.operators.OperatorDelayWithSelector": 789,
    "rx.internal.operators.OperatorDematerialize": 621,
    "rx.internal.operators.OperatorDematerializeTest": 234,
    "rx.internal.operators.OperatorDistinct": 622,
    "rx.internal.operators.OperatorDistinctTest": 235,
    "rx.internal.operators.OperatorDistinctUntilChanged": 623,
    "rx.internal.operators.OperatorDistinctUntilChangedTest": 236,
    "rx.internal.operators.OperatorDoOnEach": 456,
    "rx.internal.operators.OperatorDoOnEachTest": 302,
    "rx.internal.operators.OperatorDoOnSubscribe": 782,
    "rx.internal.operators.OperatorDoOnSubscribeTest": 783,
    "rx.internal.operators.OperatorDoOnUnsubscribe": 781,
    "rx.internal.operators.OperatorDoOnUnsubscribeTest": 784,
    "rx.internal.operators.OperatorElementAt": 587,
    "rx.internal.operators.OperatorElementAtTest": 588,
    "rx.internal.operators.OperatorFilter": 489,
    "rx.internal.operators.OperatorFilterTest": 238,
    "rx.internal.operators.OperatorFinally": 624,
    "rx.internal.operators.OperatorFinallyTest": 239,
    "rx.internal.operators.OperatorFirstTest": 240,
    "rx.internal.operators.OperatorFlatMapTest": 412,
    "rx.internal.operators.OperatorGroupBy": 435,
    "rx.internal.operators.OperatorGroupByTest": 241,
    "rx.internal.operators.OperatorLastTest": 297,
    "rx.internal.operators.OperatorMap": 433,
    "rx.internal.operators.OperatorMapNotification": 777,
    "rx.internal.operators.OperatorMapPair": 779,
    "rx.internal.operators.OperatorMapTest": 243,
    "rx.internal.operators.OperatorMaterialize": 599,
    "rx.internal.operators.OperatorMaterializeTest": 244,
    "rx.internal.operators.OperatorMerge": 434,
    "rx.internal.operators.OperatorMergeDelayError": 637,
    "rx.internal.operators.OperatorMergeDelayErrorTest": 245,
    "rx.internal.operators.OperatorMergeMaxConcurrent": 638,
    "rx.internal.operators.OperatorMergeMaxConcurrentTest": 491,
    "rx.internal.operators.OperatorMergeTest": 246,
    "rx.internal.operators.OperatorMulticast": 639,
    "rx.internal.operators.OperatorObserveOn": 478,
    "rx.internal.operators.OperatorObserveOnTest": 250,
    "rx.internal.operators.OperatorOnBackpressureBlock": 802,
    "rx.internal.operators.OperatorOnBackpressureBuffer": 752,
    "rx.internal.operators.OperatorOnBackpressureBufferTest": 760,
    "rx.internal.operators.OperatorOnBackpressureDrop": 753,
    "rx.internal.operators.OperatorOnBackpressureDropTest": 761,
    "rx.internal.operators.OperatorOnErrorFlatMap": 535,
    "rx.internal.operators.OperatorOnErrorResumeNextViaFunction": 23,
    "rx.internal.operators.OperatorOnErrorResumeNextViaFunctionTest": 251,
    "rx.internal.operators.OperatorOnErrorResumeNextViaObservable": 641,
    "rx.internal.operators.OperatorOnErrorResumeNextViaObservableTest": 252,
    "rx.internal.operators.OperatorOnErrorReturn": 642,
    "rx.internal.operators.OperatorOnErrorReturnTest": 253,
    "rx.internal.operators.OperatorOnExceptionResumeNextViaObservable": 647,
    "rx.internal.operators.OperatorOnExceptionResumeNextViaObservableTest": 254,
    "rx.internal.operators.OperatorPublish": 794,
    "rx.internal.operators.OperatorPublishTest": 795,
    "rx.internal.operators.OperatorReduceTest": 391,
    "rx.internal.operators.OperatorRepeatTest": 417,
    "rx.internal.operators.OperatorReplay": 377,
    "rx.internal.operators.OperatorReplayTest": 378,
    "rx.internal.operators.OperatorRetryTest": 256,
    "rx.internal.operators.OperatorRetryWithPredicate": 687,
    "rx.internal.operators.OperatorRetryWithPredicateTest": 688,
    "rx.internal.operators.OperatorSampleTest": 257,
    "rx.internal.operators.OperatorSampleWithObservable": 630,
    "rx.internal.operators.OperatorSampleWithTime": 631,
    "rx.internal.operators.OperatorScan": 499,
    "rx.internal.operators.OperatorScanTest": 258,
    "rx.internal.operators.OperatorSequenceEqual": 363,
    "rx.internal.operators.OperatorSequenceEqualTest": 364,
    "rx.internal.operators.OperatorSerialize": 572,
    "rx.internal.operators.OperatorSerializeTest": 576,
    "rx.internal.operators.OperatorSingle": 583,
    "rx.internal.operators.OperatorSingleTest": 386,
    "rx.internal.operators.OperatorSkip": 549,
    "rx.internal.operators.OperatorSkipLast": 207,
    "rx.internal.operators.OperatorSkipLastTest": 259,
    "rx.internal.operators.OperatorSkipLastTimed": 608,
    "rx.internal.operators.OperatorSkipLastTimedTest": 609,
    "rx.internal.operators.OperatorSkipTest": 550,
    "rx.internal.operators.OperatorSkipTimed": 649,
    "rx.internal.operators.OperatorSkipTimedTest": 260,
    "rx.internal.operators.OperatorSkipUntil": 650,
    "rx.internal.operators.OperatorSkipUntilTest": 353,
    "rx.internal.operators.OperatorSkipWhile": 562,
    "rx.internal.operators.OperatorSkipWhileTest": 261,
    "rx.internal.operators.OperatorSubscribeOn": 467,
    "rx.internal.operators.OperatorSubscribeOnTest": 468,
    "rx.internal.operators.OperatorSwitch": 658,
    "rx.internal.operators.OperatorSwitchTest": 264,
    "rx.internal.operators.OperatorTake": 426,
    "rx.internal.operators.OperatorTakeLast": 660,
    "rx.internal.operators.OperatorTakeLastTest": 662,
    "rx.internal.operators.OperatorTakeLastTimed": 661,
    "rx.internal.operators.OperatorTakeLastTimedTest": 266,
    "rx.internal.operators.OperatorTakeTest": 267,
    "rx.internal.operators.OperatorTakeTimed": 659,
    "rx.internal.operators.OperatorTakeTimedTest": 427,
    "rx.internal.operators.OperatorTakeUntil": 83,
    "rx.internal.operators.OperatorTakeUntilTest": 268,
    "rx.internal.operators.OperatorTakeWhile": 646,
    "rx.internal.operators.OperatorTakeWhileTest": 289,
    "rx.internal.operators.OperatorThrottleFirst": 645,
    "rx.internal.operators.OperatorThrottleFirstTest": 269,
    "rx.internal.operators.OperatorTimeInterval": 644,
    "rx.internal.operators.OperatorTimeIntervalTest": 290,
    "rx.internal.operators.OperatorTimeout": 494,
    "rx.internal.operators.OperatorTimeoutBase": 495,
    "rx.internal.operators.OperatorTimeoutTests": 216,
    "rx.internal.operators.OperatorTimeoutWithSelector": 496,
    "rx.internal.operators.OperatorTimeoutWithSelectorTest": 413,
    "rx.internal.operators.OperatorTimestamp": 127,
    "rx.internal.operators.OperatorTimestampTest": 359,
    "rx.internal.operators.OperatorToMap": 635,
    "rx.internal.operators.OperatorToMapTest": 334,
    "rx.internal.operators.OperatorToMultimap": 634,
    "rx.internal.operators.OperatorToMultimapTest": 335,
    "rx.internal.operators.OperatorToObservableList": 429,
    "rx.internal.operators.OperatorToObservableListTest": 272,
    "rx.internal.operators.OperatorToObservableSortedList": 430,
    "rx.internal.operators.OperatorToObservableSortedListTest": 273,
    "rx.internal.operators.OperatorUnsubscribeOn": 503,
    "rx.internal.operators.OperatorUnsubscribeOnTest": 505,
    "rx.internal.operators.OperatorWindowWithObservable": 663,
    "rx.internal.operators.OperatorWindowWithObservableTest": 797,
    "rx.internal.operators.OperatorWindowWithSize": 664,
    "rx.internal.operators.OperatorWindowWithSizeTest": 798,
    "rx.internal.operators.OperatorWindowWithStartEndObservable": 665,
    "rx.internal.operators.OperatorWindowWithStartEndObservableTest": 799,
    "rx.internal.operators.OperatorWindowWithTime": 666,
    "rx.internal.operators.OperatorWindowWithTimeTest": 800,
    "rx.internal.operators.OperatorZip": 461,
    "rx.internal.operators.OperatorZipCompletionTest": 347,
    "rx.internal.operators.OperatorZipIterable": 463,
    "rx.internal.operators.OperatorZipIterableTest": 464,
    "rx.internal.operators.OperatorZipTest": 275,
    "rx.internal.operators.SafeSubscriberTest": 265,
    "rx.internal.operators.TakeLastQueueProducer": 780,
    "rx.internal.schedulers.NewThreadWorker": 694,
    "rx.internal.schedulers.ScheduledAction": 695,
    "rx.internal.util.FrontPadding": 721,
    "rx.internal.util.IndexedRingBuffer": 730,
    "rx.internal.util.IndexedRingBufferTest": 748,
    "rx.internal.util.ObjectPool": 731,
    "rx.internal.util.PaddedAtomicInteger": 683,
    "rx.internal.util.PaddedAtomicIntegerBase": 722,
    "rx.internal.util.PlatformDependent": 801,
    "rx.internal.util.RxRingBuffer": 754,
    "rx.internal.util.RxRingBufferBase": 762,
    "rx.internal.util.RxRingBufferSpmcTest": 763,
    "rx.internal.util.RxRingBufferSpscTest": 764,
    "rx.internal.util.RxRingBufferWithoutUnsafeTest": 765,
    "rx.internal.util.RxThreadFactory": 693,
    "rx.internal.util.ScalarSynchronousObservable": 732,
    "rx.internal.util.SubscriptionIndexedRingBuffer": 733,
    "rx.internal.util.SubscriptionList": 691,
    "rx.internal.util.SubscriptionListTest": 692,
    "rx.internal.util.SubscriptionRandomList": 734,
    "rx.internal.util.SynchronizedQueue": 735,
    "rx.internal.util.SynchronizedSubscription": 736,
    "rx.internal.util.UtilityFunctions": 796,
    "rx.internal.util.unsafe.ConcurrentCircularArrayQueue": 738,
    "rx.internal.util.unsafe.ConcurrentSequencedCircularArrayQueue": 739,
    "rx.internal.util.unsafe.MessagePassingQueue": 770,
    "rx.internal.util.unsafe.MpmcArrayQueue": 743,
    "rx.internal.util.unsafe.Pow2": 744,
    "rx.internal.util.unsafe.SpmcArrayQueue": 745,
    "rx.internal.util.unsafe.SpscArrayQueue": 746,
    "rx.internal.util.unsafe.UnsafeAccess": 747,
    "rx.jmh.InputWithIncrementingInteger": 671,
    "rx.jmh.LatchedObserver": 724,
    "rx.observables.BlockingObservable": 139,
    "rx.observables.BlockingObservablePerf": 785,
    "rx.observables.BlockingObservableTest": 222,
    "rx.observables.ConnectableObservable": 121,
    "rx.observables.GroupedObservable": 87,
    "rx.observers.Observers": 439,
    "rx.observers.SafeObserverTest": 393,
    "rx.observers.SafeSubscriber": 13,
    "rx.observers.SerializedObserver": 582,
    "rx.observers.SerializedObserverTest": 579,
    "rx.observers.SerializedSubscriber": 571,
    "rx.observers.Subscribers": 462,
    "rx.observers.TestObserver": 442,
    "rx.observers.TestObserverTest": 443,
    "rx.observers.TestSubscriber": 453,
    "rx.observers.TestSubscriberTest": 454,
    "rx.operators.OperationCache": 597,
    "rx.operators.OperationFirstOrDefaultTest": 603,
    "rx.operators.OperationLastTest": 604,
    "rx.operators.OperationSingle": 598,
    "rx.operators.OperationSingleTest": 605,
    "rx.operators.OperatorFlatMapPerf": 725,
    "rx.operators.OperatorMapPerf": 455,
    "rx.operators.OperatorMergePerf": 726,
    "rx.operators.OperatorObserveOnPerf": 727,
    "rx.operators.OperatorRangePerf": 757,
    "rx.operators.OperatorSerializePerf": 594,
    "rx.operators.Tester": 110,
    "rx.package-info": 60,
    "rx.plugins.RxJavaErrorHandler": 77,
    "rx.plugins.RxJavaObservableExecutionHook": 114,
    "rx.plugins.RxJavaObservableExecutionHookDefault": 115,
    "rx.plugins.RxJavaPlugins": 79,
    "rx.plugins.RxJavaPluginsTest": 281,
    "rx.plugins.RxJavaSchedulersHook": 778,
    "rx.schedulers.AbstractSchedulerConcurrencyTests": 407,
    "rx.schedulers.AbstractSchedulerTests": 404,
    "rx.schedulers.CachedThreadScheduler": 680,
    "rx.schedulers.CachedThreadSchedulerTest": 681,
    "rx.schedulers.ComputationSchedulerPerf": 672,
    "rx.schedulers.ComputationSchedulerTests": 380,
    "rx.schedulers.EventLoopsScheduler": 606,
    "rx.schedulers.ExecutorScheduler": 689,
    "rx.schedulers.ExecutorSchedulerTest": 690,
    "rx.schedulers.GenericScheduledExecutorService": 125,
    "rx.schedulers.IOSchedulerPerf": 728,
    "rx.schedulers.ImmediateScheduler": 99,
    "rx.schedulers.ImmediateSchedulerTest": 221,
    "rx.schedulers.NewThreadScheduler": 100,
    "rx.schedulers.NewThreadSchedulerTest": 405,
    "rx.schedulers.SchedulerTests": 793,
    "rx.schedulers.Schedulers": 101,
    "rx.schedulers.SleepingAction": 96,
    "rx.schedulers.TestScheduler": 118,
    "rx.schedulers.TestSchedulerTest": 408,
    "rx.schedulers.TimeInterval": 218,
    "rx.schedulers.Timestamped": 126,
    "rx.schedulers.TrampolineScheduler": 458,
    "rx.schedulers.TrampolineSchedulerTest": 220,
    "rx.schedulers.package-info": 59,
    "rx.subjects.AsyncSubject": 128,
    "rx.subjects.AsyncSubjectTest": 282,
    "rx.subjects.BehaviorSubject": 133,
    "rx.subjects.BehaviorSubjectTest": 283,
    "rx.subjects.PublishSubject": 123,
    "rx.subjects.PublishSubjectTest": 284,
    "rx.subjects.RepeatSubject": 112,
    "rx.subjects.ReplaySubject": 147,
    "rx.subjects.ReplaySubjectBoundedConcurrencyTest": 679,
    "rx.subjects.ReplaySubjectConcurrencyTest": 388,
    "rx.subjects.ReplaySubjectPerf": 601,
    "rx.subjects.ReplaySubjectTest": 285,
    "rx.subjects.SerializedSubject": 790,
    "rx.subjects.SerializedSubjectTest": 791,
    "rx.subjects.Subject": 111,
    "rx.subjects.SubjectSubscriptionManager": 387,
    "rx.subjects.TestSubject": 586,
    "rx.subscriptions.BooleanSubscription": 90,
    "rx.subscriptions.CompositeSubscription": 124,
    "rx.subscriptions.CompositeSubscriptionTest": 286,
    "rx.subscriptions.MultipleAssignmentSubscription": 194,
    "rx.subscriptions.MultipleAssignmentSubscriptionTest": 365,
    "rx.subscriptions.RefCountSubscription": 357,
    "rx.subscriptions.RefCountSubscriptionTest": 366,
    "rx.subscriptions.SerialSubscription": 214,
    "rx.subscriptions.SerialSubscriptionTests": 215,
    "rx.subscriptions.Subscriptions": 91,
    "rx.subscriptions.SubscriptionsTest": 287,
    "rx.test.OperatorTester": 291,
    "rx.testing.UnsubscribeTester": 113,
    "rx.util.AssertObservable": 349,
    "rx.util.AssertObservableTest": 351
}